server.py
mseep_cbi_mcp_server-0.1.1.dist-info/METADATA
mseep_cbi_mcp_server-0.1.1.dist-info/WHEEL
mseep_cbi_mcp_server-0.1.1.dist-info/entry_points.txt
mseep_cbi_mcp_server-0.1.1.dist-info/top_level.txt
mseep_cbi_mcp_server-0.1.1.dist-info/RECORD
