Metadata-Version: 2.4
Name: mseep-cbi-mcp-server
Version: 0.1.1
Summary: MCP Server for interacting with ChatCBI
Author-email: mseep <support@skydeck.ai>
Requires-Python: >=3.12
Requires-Dist: httpx==0.28.1
Requires-Dist: mcp[cli]==1.8.1
Requires-Dist: python-dotenv==1.1.0
